story_map/__init__.py
story_map/admin.py
story_map/apps.py
story_map/import_utils.py
story_map/models.py
story_map/tests.py
story_map/urls.py
story_map/views.py
story_map/data/sample.json
story_map/data/sample1.json
story_map/management/commands/__init__.py
story_map/management/commands/story_map_from_url.py
story_map/migrations/0001_initial.py
story_map/migrations/__init__.py
story_map/templates/story_map/story_detail.html
django_story_map-0.6.2.dist-info/METADATA
django_story_map-0.6.2.dist-info/WHEEL
django_story_map-0.6.2.dist-info/top_level.txt
django_story_map-0.6.2.dist-info/RECORD
