Metadata-Version: 2.1
Name: django-story-map
Version: 0.6.2
Summary: A django app to create/edit/publish story maps using https://storymap.knightlab.com/
Home-page: https://github.com/acdh-oeaw/django-story-map
Author: Peter Andorfer
Author-email: peter.andorfer@oeaw.ac.at
License: MIT
Keywords: django-story-map
Platform: UNKNOWN
Requires-Dist: Django (<5,>=3.2)
